SensitiveImgDetect/__init__.py
SensitiveImgDetect/model_v2.pickle
SensitiveImgDetect/transform.pickle
SensitiveImgDetect-0.0.2.dist-info/METADATA
SensitiveImgDetect-0.0.2.dist-info/WHEEL
SensitiveImgDetect-0.0.2.dist-info/top_level.txt
SensitiveImgDetect-0.0.2.dist-info/RECORD
